latch_o11y/__init__.py
latch_o11y/o11y.py
latch_o11y/py.typed
latch_o11y-1.2.0.dist-info/METADATA
latch_o11y-1.2.0.dist-info/WHEEL
latch_o11y-1.2.0.dist-info/licenses/LICENSE
latch_o11y-1.2.0.dist-info/RECORD
